Workbook

Sheet Raw_Data
A1: Order ID | B1: Order Date | C1: Ship Date | D1: Ship Mode | E1: Customer Name | F1: Segment | G1: Region | H1: City | I1: Category | J1: Sub-Category | K1: Product Name | L1: Quantity | M1: Unit Price | N1: Discount | O1: Sales | P1: Profit
A2: ORD-10216 | B2: 45312 | C2: 45319 | D2: Second Class | E2: IMRAN KHAN | F2: Home Office | G2: East | H2: Sialkot | I2: Technology | J2: Machines | K2: Label Maker | L2: 3 | M2: 641.93 | N2: 0 | O2: 1925.79 | P2: -246.6
A3: ORD-11062 | B3: 45137 | C3: 45140 | D3: Second Class | E3: Fatima Raza | F3: Corporate | G3: South | H3: Hyderabad | I3: Furniture | J3: Furnishings | K3: Desk Lamp | L3: 6 | M3: 367.57 | N3: 0 | O3: 2205.42 | P3: 457.55
A4: ORD-11190 | B4: 45329 | C4: 45335 | D4: Second Class | E4: Zara Iqbal | F4: Consumer | G4: East | H4: Gujranwala | I4: Technology | J4: Copiers | K4: Desktop Copier | L4: 10 | M4: 139.55 | N4: 0 | O4: 1395.5 | P4: 155.48
A5: ORD-10669 | B5: 45355 | C5: 45357 | D5: Second Class | E5: Hina Sheikh | F5: Corporate | G5: East | H5: Sialkot | I5: Furniture | J5: Chairs | K5: Executive Leather Chair | L5: 5 | M5: 427.49 | N5: 0.15 | O5: 2137.45 | P5: -212.93
A6: ORD-10840 | B6: 45186 | C6: 45191 | D6: Standard Class | F6: Home Office | G6: Nort | H6: Islamabad | I6: Furniture | J6: Bookcases | K6: Corner Bookcase | L6: 1 | M6: 896.19 | N6: 0.2 | O6: 896.19 | P6: -21.04
A7: ORD-11011 | B7: 45371 | C7: 45377 | D7: Standard Class | E7: Omar Raza | F7: Home Office | G7: east | H7: Sialkot | I7: Office Supplies | J7: Labels | K7: Address Labels | L7: 10 | M7: 682.06 | N7: 0 | O7: 6820.6 | P7: 1989.09
A8: ORD-10492 | B8: 45236 | C8: 45241 | D8: Standard Class | E8: Zara Qureshi | F8: Home Office | G8: east | H8: Gujranwala | I8: Furniture | J8: Furnishings | K8: Wall Clock | L8: 9 | M8: 410.64 | N8: 0.3 | O8: 3695.76 | P8: 457.47
A9: ORD-10172 | B9: 45275 | C9: 45280 | D9: Same Day | E9: Imran Sheikh | F9: Consumer | G9: Centeral | H9: Faisalabad | I9: Furniture | J9: Bookcases | K9: Wall-Mount Bookcase | L9: 6 | M9: 499.97 | N9: 0.1 | O9: 2999.82 | P9: 197.76
A10: ORD-10063 | B10: 45422 | C10: 45425 | D10: First Class | E10: Usman Qureshi | F10: Home Office | G10: EAST | H10: Gujranwala | I10: Office Supplies | J10: Storage | K10: Storage Box | L10: 7 | M10: 214.04 | N10: 0.3 | O10: 1498.28 | P10: 82.99
A11: ORD-10681 | B11: 45339 | C11: 45340 | D11: Standard Class | E11: Nida Khan | F11: Consumer | G11: central | H11: Multan | I11: Technology | J11: Phones | K11: Office Desk Phone | L11: 2 | M11: 744.77 | N11: 0.3 | O11: 1489.54 | P11: 395.11
A12: ORD-10051 | B12: 45537 | C12: 45544 | D12: Standard Class | E12: Mahnoor Iqbal | F12: Consumer | G12: central | H12: Faisalabad | I12: Office Supplies | J12: Art | K12: Pen Set | L12: 5 | M12: 513.92 | N12: 0 | O12: 2569.6 | P12: 397.81
A13: ORD-10650 | B13: 45488 | C13: 45492 | D13: Second Class | E13: Zara Butt | F13: Corporate | G13: NORTH | H13: Rawalpindi | I13: Furniture | J13: Bookcases | K13: Wall-Mount Bookcase | L13: 4 | M13: 249.91 | N13: 0 | O13: 999.64 | P13: 38.56
A14: ORD-11127 | B14: 45409 | C14: 45416 | D14: Standard Class | E14: Ahmed Malik | F14: Consumer | G14: SOUTH | H14: Hyderabad | I14: Furniture | J14: Furnishings | K14: Floor Mat | L14: 2 | M14: 510.82 | N14: 0 | O14: 1021.64 | P14: -35.09
A15: ORD-10677 | B15: 45012 | C15: 45018 | D15: First Class | E15: Hina Khan | F15: Consumer | G15: CENTRAL | H15: Multan | I15: Office Supplies | J15: Labels | K15: Shipping Labels | L15: 11 | M15: 735.25 | N15: 0.3 | O15: 8087.75 | P15: 224.37
A16: ORD-10170 | B16: 44974 | C16: 44975 | D16: Standard Class | E16: Fatima Qureshi | F16: Corporate | G16: EAST | H16: Sialkot | I16: Furniture | J16: Bookcases | K16: 5-Shelf Bookcase | L16: 3 | M16: 678.27 | N16: 0.2 | O16: 2034.81 | P16: 529.97
A17: ORD-10374 | B17: 44957 | C17: 44964 | D17: First Class | E17: Zara Butt | F17: Home Office | G17: east | H17: Gujranwala | I17: Office Supplies | J17: Art | K17: Highlighter Pack | L17: 4 | M17: 100.56 | N17: 0 | O17: 402.24 | P17: -55.07
A18: ORD-10395 | B18: 45464 | C18: 45467 | D18: First Class | E18: Sana Ansari | F18: Corporate | G18: South | H18: Hyderabad | I18: Furniture | J18: Tables | K18: Round Conference Table | L18: 1 | M18: 720.13 | N18: 0.15 | O18: 720.13 | P18: -52.54
... A23: ORD-10651 | B23: 45034 | C23: 45041 | D23: First Class | E23: Imran Malik | F23: Home Office | G23: north | H23: Rawalpindi | I23: Technology | J23: Accessories | K23: Keyboard | L23: 9 | M23: 317.27 | N23: 0.15 | O23: 2855.43 | P23: 807.23
A24: ORD-10420 | B24: 45372 | C24: 45373 | E24: Ali Malik | F24: Corporate | G24: east | H24: Gujranwala | I24: Technology | J24: Accessories | K24: Keyboard | L24: 9 | M24: 575.49 | N24: 0.3 | O24: 5179.41 | P24: 341.29
A25: ORD-10252 | B25: 45620 | C25: 45625 | D25: First Class | E25: Adeel Qureshi | F25: Corporate | G25: Centeral | H25: Multan | I25: Furniture | J25: Bookcases | K25: Corner Bookcase | L25: 5 | M25: 272.14 | N25: 0 | O25: 1360.7 | P25: 123.65
A26: ORD-10385 | B26: 45116 | C26: 45118 | D26: First Class | E26: Hina Malik | F26: Home Office | G26: NORTH | H26: Lahore | I26: Furniture | J26: Chairs | K26: Folding Chair | L26: 1 | M26: 102.45 | N26: 0 | O26: 102.45 | P26: -7.1
A27: ORD-10204 | B27: 45210 | C27: 45216 | D27: Same Day | E27: Ahmed Chaudhry | F27: Corporate | G27: north | H27: Rawalpindi | I27: Technology | J27: Accessories | K27: Keyboard | L27: 4 | M27: 468.39 | N27: 0.15 | O27: 1873.56 | P27: -104.31
A28: ORD-10325 | B28: 45562 | C28: 45565 | D28: Standard Class | E28: Usman Qureshi | F28: Home Office | G28: WEST | H28: Peshawar | I28: Furniture | J28: Bookcases | K28: Wall-Mount Bookcase | L28: 3 | M28: 53.46 | N28: 0.3 | O28: 160.38 | P28: 9.88
A29: ORD-11015 | B29: 45254 | C29: 45257 | D29: Second Class | E29: Ahmed Iqbal | F29: Consumer | G29: West | H29: Quetta | I29: Technology | J29: Accessories | K29: Wireless Mouse | L29: 9 | M29: 65.83 | N29: 0 | O29: 592.47 | P29: 85.81
A30: ORD-11129 | B30: 45214 | C30: 45220 | D30: Second Class | E30: Adeel Malik | F30: Consumer | G30: Centeral | H30: Multan | I30: Furniture | J30: Bookcases | K30: 5-Shelf Bookcase | L30: -2 | M30: 725.85 | N30: 0.3 | O30: 1451.7 | P30: 216.54
A31: ORD-10714 | B31: 45517 | C31: 45518 | D31: First Class | E31: Ayesha Farooq | F31: Home Office | G31: east | H31: Sialkot | I31: Office Supplies | J31: Storage | K31: Storage Bin | L31: 11 | M31: 899.15 | N31: 0.1 | O31: 9890.65 | P31: 545.9
A32: ORD-10881 | B32: 44960 | C32: 44966 | D32: Standard Class | E32: Tariq Malik | F32: Corporate | G32: West | H32: Peshawar | I32: Furniture | J32: Furnishings | K32: Wall Clock | L32: 12 | M32: 700.05 | N32: 0.2 | O32: 8400.6 | P32: 2894.88
A33: ORD-10611 | B33: 45222 | C33: 45229 | D33: Second Class | E33: Fatima Ansari | F33: Home Office | G33: north | H33: Rawalpindi | I33: Office Supplies | J33: Storage | K33: Storage Box | L33: 1 | M33: 816.44 | N33: 0.2 | O33: 816.44 | P33: 281.01
A34: ORD-10034 | B34: 45443 | C34: 45447 | D34: Second Class | E34: Zara Sheikh | F34: Corporate | G34: Centeral | H34: Multan | I34: Technology | J34: Copiers | K34: Multifunction Copier | L34: 11 | M34: 253.19 | N34: 0.3 | O34: 2785.09 | P34: 308.17
A35: ORD-10757 | B35: 45217 | C35: 45224 | D35: Same Day | E35: Fatima Iqbal | F35: Corporate | G35: central | H35: Multan | I35: Technology | J35: Accessories | K35: USB Cable | L35: 10 | M35: 826.84 | N35: 0 | O35: 8268.4 | P35: -335.46
A36: ORD-10922 | B36: 45321 | C36: 45327 | D36: First Class | E36: Usman Butt | F36: Consumer | G36: north | H36: Lahore | I36: Furniture | J36: Tables | K36: Round Conference Table | L36: 7 | M36: 293.67 | N36: 0.15 | O36: 2055.69 | P36: 185.81
... A45: ORD-10934 | B45: 45209 | C45: 45212 | D45: Same Day | E45: Sara Khan | F45: Consumer | G45: CENTRAL | H45: Faisalabad | I45: Technology | J45: Accessories | K45: Wireless Mouse | L45: 2 | M45: 643.22 | N45: 0.1 | O45: 1286.44 | P45: -36.83
A46: ORD-10264 | B46: 45357 | C46: 45363 | D46: Standard Class | E46: Ayesha Ansari | F46: Corporate | G46: Nort | H46: Islamabad | I46: Technology | J46: Machines | K46: Label Maker | L46: 12 | M46: 557.84 | N46: 0 | O46: 6694.08
A47: ORD-11111 | B47: 45144 | C47: 45149 | D47: First Class | E47: Tariq Malik | F47: Home Office | G47: north | H47: Lahore | I47: Office Supplies | J47: Storage | K47: Storage Bin | L47: 12 | M47: 496.3 | N47: 0.15 | O47: 5955.6 | P47: 1698.24
A48: ORD-10796 | B48: 45310 | C48: 45314 | D48: First Class | E48: Omar Butt | F48: Home Office | G48: EAST | H48: Sialkot | I48: Furniture | J48: Bookcases | K48: 5-Shelf Bookcase | L48: 10 | M48: 27.85 | N48: 0.15 | O48: 278.5 | P48: -12.33
A49: ORD-10565 | B49: 45432 | C49: 45435 | D49: Second Class | E49: Fatima Iqbal | F49: Home Office | G49: NORTH | H49: Islamabad | I49: Technology | J49: Machines | K49: Laser Printer | L49: 2 | M49: 783.58 | N49: 0.15 | O49: 1567.16 | P49: 156.97
A50: ORD-10640 | B50: 45412 | C50: 45414 | D50: Second Class | E50: Faisal Butt | F50: Corporate | G50: North | H50: Rawalpindi | I50: Technology | J50: Accessories | K50: Keyboard | L50: 11 | M50: 651.68 | N50: 0 | O50: 7168.48 | P50: -953.43
A51: ORD-11054 | B51: 45187 | C51: 45192 | D51: Same Day | E51: Ahmed Malik | F51: Home Office | G51: NORTH | H51: Lahore | I51: Office Supplies | J51: Labels | K51: Shipping Labels | L51: 4 | M51: 731.73 | N51: 0 | O51: 2926.92 | P51: 918.77
A52: ORD-10656 | B52: 45219 | C52: 45224 | D52: Same Day | E52: Imran Ansari | F52: Consumer | G52: West | H52: Peshawar | I52: Technology | J52: Machines | K52: Label Maker | L52: 11 | M52: 898.17 | N52: 0.15 | O52: 9879.87 | P52: 1965.51
A53: ORD-10671 | B53: 45592 | C53: 45595 | D53: Standard Class | E53: Ali Qureshi | F53: Consumer | G53: South | H53: Karachi | I53: Furniture | J53: Tables | K53: Round Conference Table | L53: 11 | M53: 736.58 | N53: 0 | O53: 8102.38 | P53: 1639.35
A54: ORD-10189 | B54: 45239 | C54: 45240 | D54: Second Class | E54: Adeel Butt | F54: Home Office | G54: SOUTH | H54: Karachi | I54: Technology | J54: Copiers | K54: Multifunction Copier | L54: 10 | M54: 348.42 | N54: 0 | O54: 3484.2 | P54: 325.2
A55: ORD-10141 | B55: 45133 | C55: 45140 | D55: Standard Class | E55: Usman Khan | F55: Consumer | G55: CENTRAL | H55: Faisalabad | I55: Furniture | J55: Chairs | K55: Mesh Task Chair | L55: 11 | M55: 815.14 | N55: 0 | O55: 8966.54 | P55: 1515.1
A56: ORD-10418 | B56: 45536 | C56: 45543 | D56: First Class | E56: Sana Butt | F56: Consumer | G56: South | H56: Hyderabad | I56: Office Supplies | J56: Paper | K56: Notebook | L56: 4 | M56: 522.09 | N56: 0.3 | O56: 2088.36 | P56: 47.07
A57: ORD-10522 | B57: 45466 | C57: 45472 | D57: Second Class | E57: Imran Chaudhry | F57: Home Office | G57: Central | H57: Faisalabad | I57: Office Supplies | J57: Art | K57: Marker Set | L57: 3 | M57: 885.85 | N57: 0.2 | O57: 2657.55 | P57: 801.12
A58: ORD-10263 | B58: 45037 | C58: 45043 | E58: Nida Malik | F58: Corporate | G58: North | H58: Rawalpindi | I58: Furniture | J58: Furnishings | K58: Wall Clock | L58: 9 | M58: 231.2 | N58: 0.2 | O58: 2080.8 | P58: -152.81
A59: ORD-11087 | B59: 44929 | C59: 44933 | D59: Standard Class | E59: Kamran Qureshi | F59: Home Office | G59: South | H59: Karachi | I59: Office Supplies | J59: Storage | K59: Storage Bin | L59: 2 | M59: 41.18 | N59: 0 | O59: 82.36 | P59: 1.24
A60: ORD-10546 | B60: 45305 | C60: 45311 | D60: Same Day | E60: Faisal Farooq | F60: Consumer | G60: Centeral | H60: Faisalabad | I60: Office Supplies | J60: Labels | K60: Shipping Labels | L60: 12 | M60: 838.28 | N60: 0.1 | O60: 10059.36 | P60: 2171.4
A61: ORD-10819 | B61: 45546 | C61: 45551 | D61: Second Class | E61: Tariq Malik | F61: Consumer | G61: North | H61: Islamabad | I61: Furniture | J61: Bookcases | K61: Wall-Mount Bookcase | L61: 11 | M61: 49.05 | N61: 0 | O61: 539.55 | P61: 16.75
A62: ORD-10280 | B62: 45487 | C62: 45494 | D62: First Class | E62: Kamran Butt | F62: Home Office | G62: EAST | H62: Sialkot | I62: Furniture | J62: Tables | K62: Coffee Table | L62: 12 | M62: 586.83 | N62: 0 | O62: 7041.96 | P62: 717.9
A63: ORD-10595 | B63: 44997 | C63: 45001 | D63: Same Day | E63: Imran Butt | F63: Corporate | G63: south | H63: Karachi | I63: Office Supplies | J63: Art | K63: Highlighter Pack | L63: 10 | M63: 519.71 | N63: 0 | O63: 5197.1 | P63: 747.06
A64: ORD-10027 | B64: 45194 | C64: 45196 | D64: Second Class | E64: Hina Iqbal | F64: Corporate | G64: CENTRAL | H64: Multan | I64: Furniture | J64: Furnishings | K64: Wall Clock | L64: 10 | M64: 885.89 | N64: 0 | O64: 8858.9 | P64: 377.37
A65: ORD-11193 | B65: 45551 | C65: 45556 | D65: Same Day | E65: Tariq Ansari | F65: Consumer | G65: Central | H65: Multan | I65: Office Supplies | J65: Storage | K65: Filing Cabinet | L65: 8 | M65: 866.37 | N65: 0.3 | O65: 6930.96 | P65: 2124.06
A66: ORD-10498 | B66: 45019 | C66: 45021 | D66: First Class | E66: Usman Iqbal | F66: Corporate | G66: Central | H66: Faisalabad | I66: Office Supplies | J66: Labels | K66: Shipping Labels | L66: 4 | M66: 134.13 | N66: 0 | O66: N/A | P66: -23.04
A67: ORD-10727 | B67: 45300 | C67: 45301 | D67: First Class | E67: Bilal Chaudhry | F67: Corporate | G67: South | H67: Hyderabad | I67: Furniture | J67: Tables | K67: Round Conference Table | L67: 5 | M67: 436.01 | N67: 0 | O67: 2180.05 | P67: 52.92
A68: ORD-10489 | B68: 44947 | C68: 44953 | D68: Second Class | E68: hina qureshi | F68: Corporate | G68: West | H68: Peshawar | I68: Office Supplies | J68: Labels | K68: Shipping Labels | L68: 2 | M68: 728.45 | N68: 0 | O68: 1456.9 | P68: 284.72
A69: ORD-10412 | B69: 45290 | C69: 45292 | D69: Standard Class | E69: Rabia Chaudhry | F69: Home Office | G69: South | H69: Karachi | I69: Technology | J69: Copiers | K69: Desktop Copier | L69: 7 | M69: 834.28 | N69: 0.15 | O69: 5839.96 | P69: 195.55
A70: ORD-11157 | B70: 45463 | C70: 45464 | D70: Second Class | E70: Omar Qureshi | F70: Corporate | G70: South | H70: Hyderabad | I70: Office Supplies | J70: Art | K70: Pen Set | L70: 2 | M70: 864.53 | N70: 0.1 | O70: 1729.06 | P70: 533.13
A71: ORD-11172 | B71: 44930 | C71: 44933 | E71: Ahmed Ansari | F71: Corporate | G71: West | H71: Quetta | I71: Technology | J71: Copiers | K71: Multifunction Copier | L71: 3 | M71: 368.58 | N71: 0.3 | O71: 1105.74 | P71: 32.47
A72: ORD-11169 | B72: 45032 | C72: 45035 | D72: First Class | E72: Fatima Malik | F72: Consumer | G72: Nort | H72: Islamabad | I72: Technology | J72: Machines | K72: Laser Printer | L72: 3 | M72: 756.07 | N72: 0.3 | O72: 2268.21 | P72: 589.02
A73: ORD-10046 | B73: 45495 | C73: 45502 | D73: First Class | E73: Omar Sheikh | F73: Corporate | G73: South | H73: Hyderabad | I73: Office Supplies | J73: Binders | K73: 3-Ring Binder | L73: 7 | M73: 624.15 | N73: 0 | O73: 4369.05 | P73: 795.08
A74: ORD-10113 | B74: 45417 | C74: 45423 | D74: First Class | E74: Omar Sheikh | F74: Home Office | G74: south | H74: Karachi | I74: Technology | J74: Copiers | K74: Desktop Copier | L74: 1 | M74: 713.04 | N74: 0 | O74: 713.04 | P74: 5.56
A75: ORD-10467 | B75: 45451 | C75: 45457 | D75: First Class | E75: Hina Farooq | F75: Corporate | G75: Central | H75: Faisalabad | I75: Furniture | J75: Chairs | K75: Mesh Task Chair | L75: 12 | M75: 126.27 | N75: 0 | O75: 1515.24 | P75: -187.22
A76: ORD-10547 | B76: 45074 | C76: 45079 | D76: Standard Class | E76: Sana Farooq | F76: Home Office | G76: South | H76: Hyderabad | I76: Furniture | J76: Chairs | K76: Mesh Task Chair | L76: 1 | M76: 673.11 | N76: 0.15 | O76: 673.11 | P76: 23.33
A77: ORD-10771 | B77: 45089 | C77: 45091 | D77: Same Day | E77: Usman Sheikh | F77: Corporate | G77: North | H77: Islamabad | I77: Technology | J77: Copiers | K77: Multifunction Copier | L77: 2 | M77: 810.32 | N77: 0 | O77: 1620.64 | P77: 346.95
A78: ORD-11160 | B78: 45172 | C78: 45176 | D78: Same Day | E78: Zara Khan | F78: Home Office | G78: east | H78: Gujranwala | I78: Office Supplies | J78: Binders | K78: 3-Ring Binder | L78: 12 | M78: 672.68 | N78: 0.2 | O78: 8072.16 | P78: -24.42
A79: ORD-10101 | B79: 45010 | C79: 45015 | D79: Second Class | E79: Adeel Malik | F79: Home Office | G79: SOUTH | H79: Hyderabad | I79: Technology | J79: Copiers | K79: Desktop Copier | L79: 5 | M79: 505.24 | N79: 0.2 | O79: 2526.2 | P79: 621.02
A80: ORD-10379 | B80: 45572 | C80: 45573 | D80: Second Class | E80: Sana Butt | F80: Corporate | G80: SOUTH | H80: Hyderabad | I80: Office Supplies | J80: Storage | K80: Filing Cabinet | L80: 7 | M80: 268.51 | N80: 0 | O80: 1879.57 | P80: 366.47
A81: ORD-10663 | B81: 44968 | C81: 44970 | D81: Second Class | E81: Imran Chaudhry | F81: Corporate | G81: West | H81: Peshawar | I81: Furniture | J81: Tables | K81: Rectangular Desk | L81: 2 | M81: 381.88 | N81: 0.15 | O81: 763.76 | P81: 74.68
A82: ORD-10128 | B82: 45402 | C82: 45404 | D82: First Class | E82: Kamran Iqbal | F82: Consumer | G82: EAST | H82: Sialkot | I82: Office Supplies | J82: Storage | K82: Storage Bin | L82: 3 | M82: 685.8 | N82: 0.15 | O82: 2057.4 | P82: 269.16
A83: ORD-10098 | B83: 45535 | C83: 45540 | D83: First Class | E83: Hina Qureshi | F83: Home Office | G83: West | H83: Quetta | I83: Office Supplies | J83: Labels | K83: Address Labels | L83: 8 | M83: 453.72 | N83: 0 | O83: 3629.76 | P83: 273.18
... A97: ORD-10179 | B97: 45175 | C97: 45178 | D97: Same Day | E97: Fatima Qureshi | F97: Home Office | G97: WEST | H97: Peshawar | I97: Office Supplies | J97: Binders | K97: Hanging Binder | L97: 9 | M97: 166.03 | N97: 0.3 | O97: 1494.27 | P97: 186.86
A98: ORD-10060 | B98: 45089 | C98: 45092 | D98: First Class | E98: Sana Malik | F98: Home Office | G98: Central | H98: Faisalabad | I98: Furniture | J98: Tables | K98: Round Conference Table | L98: 11 | M98: 749.77 | N98: 0.1 | O98: 8247.47
A99: ORD-10471 | B99: 45298 | C99: 45300 | D99: First Class | E99: Ayesha Sheikh | F99: Consumer | G99: WEST | H99: Quetta | I99: Technology | J99: Accessories | K99: USB Cable | L99: 3 | M99: 771.85 | N99: 0 | O99: 2315.55 | P99: 449.27
A100: ORD-10430 | B100: 45326 | C100: 45327 | D100: Same Day | E100: Bilal Khan | F100: Consumer | G100: east | H100: Sialkot | I100: Technology | J100: Copiers | K100: Desktop Copier | L100: 4 | M100: 27.7 | N100: 0.15 | O100: 110.8 | P100: -3.41
A101: ORD-11178 | B101: 45304 | C101: 45306 | D101: Second Class | E101: Adeel Chaudhry | F101: Home Office | G101: east | H101: Sialkot | I101: Office Supplies | J101: Art | K101: Pen Set | L101: 7 | M101: 150.27 | N101: 0.2 | O101: 1051.89 | P101: 338.15
A102: ORD-10284 | B102: 45562 | C102: 45569 | D102: Second Class | E102: Fatima Chaudhry | F102: Home Office | G102: west | H102: Peshawar | I102: Technology | J102: Machines | K102: Shredder | L102: 8 | M102: 163.8 | N102: 0.2 | O102: 1310.4 | P102: -147.77
A103: ORD-10983 | B103: 45606 | C103: 45608 | D103: First Class | E103: Nida Farooq | F103: Corporate | G103: West | H103: Quetta | I103: Furniture | J103: Furnishings | K103: Wall Clock | L103: 3 | M103: 691.59 | N103: 0.15 | O103: 2074.77
A104: ORD-10731 | B104: 45178 | C104: 45179 | D104: First Class | E104: Ahmed Raza | F104: Consumer | G104: SOUTH | H104: Hyderabad | I104: Furniture | J104: Bookcases | K104: 5-Shelf Bookcase | L104: -12 | M104: 14.76 | N104: 0 | O104: 177.12 | P104: -7.64
A105: ORD-11185 | B105: 45334 | C105: 45338 | D105: Standard Class | E105: Rabia Butt | F105: Corporate | G105: Central | H105: Multan | I105: Office Supplies | J105: Art | K105: Highlighter Pack | L105: 3 | M105: 72.28 | N105: 0.3 | O105: 216.84 | P105: -15.02
A106: ORD-11026 | B106: 45592 | C106: 45593 | D106: Second Class | E106: Kamran Malik | F106: Corporate | G106: Centeral | H106: Faisalabad | I106: Furniture | J106: Chairs | K106: Folding Chair | L106: 10 | M106: 333.73 | N106: 0.3 | O106: 3337.3 | P106: 287.8
A107: ORD-10109 | B107: 45222 | C107: 45224 | D107: Standard Class | E107: Adeel Farooq | F107: Home Office | G107: East | H107: Sialkot | I107: Furniture | J107: Furnishings | K107: Floor Mat | L107: 2 | M107: 104.22 | N107: 0.1 | O107: 208.44 | P107: 30.93
A108: ORD-10783 | B108: 45597 | C108: 45599 | D108: First Class | E108: Sara Malik | F108: Consumer | G108: East | H108: Gujranwala | I108: Office Supplies | J108: Binders | K108: Hanging Binder | L108: 5 | M108: 844.84 | N108: 0 | O108: 4224.2 | P108: 411.71
A109: ORD-10597 | B109: 45020 | C109: 45023 | D109: Same Day | E109: Faisal Sheikh | F109: Home Office | G109: WEST | H109: Peshawar | I109: Office Supplies | J109: Labels | K109: Address Labels | L109: 3 | M109: 810.47 | N109: 0.2 | O109: 2431.41 | P109: 160.57
A110: ORD-10769 | B110: 45598 | C110: 45600 | E110: OMAR IQBAL | F110: Home Office | G110: EAST | H110: Gujranwala | I110: Office Supplies | J110: Paper | K110: Sticky Notes | L110: 2 | M110: 824.96 | N110: 0.2 | O110: 1649.92 | P110: 151.58
A111: ORD-11055 | B111: 45524 | C111: 45531 | D111: Standard Class | E111: Faisal Farooq | F111: Consumer | G111: EAST | H111: Gujranwala | I111: Furniture | J111: Bookcases | K111: 5-Shelf Bookcase | L111: 10 | M111: 101.73 | N111: 0.1 | O111: 1017.3 | P111: 44.19
A112: ORD-10544 | B112: 45274 | C112: 45276 | E112: Mahnoor Butt | F112: Home Office | G112: central | H112: Faisalabad | I112: Office Supplies | J112: Storage | K112: Storage Bin | L112: 12 | M112: 343.01 | N112: 0.2 | O112: 4116.12 | P112: -107.77
A113: ORD-10569 | B113: 45158 | C113: 45164 | D113: Standard Class | E113: Omar Malik | F113: Home Office | G113: West | H113: Quetta | I113: Furniture | J113: Tables | K113: Coffee Table | L113: -11 | M113: 564.64 | N113: 0 | O113: 6211.04 | P113: 558.89
A114: ORD-10901 | B114: 45418 | C114: 45424 | D114: First Class | E114: Usman Chaudhry | F114: Corporate | G114: Centeral | H114: Multan | I114: Technology | J114: Copiers | K114: Multifunction Copier | L114: 10 | M114: 529.57 | N114: 0 | O114: 5295.7 | P114: -525.76
A115: ORD-11189 | B115: 45077 | C115: 45084 | D115: Second Class | E115: Sara Butt | F115: Consumer | G115: NORTH | H115: Lahore | I115: Office Supplies | J115: Labels | K115: Address Labels | L115: 3 | M115: 205.4 | N115: 0 | O115: 616.2 | P115: 8.59
A116: ORD-10396 | B116: 45463 | C116: 45466 | D116: First Class | E116: Ali Farooq | F116: Consumer | G116: East | H116: Sialkot | I116: Technology | J116: Machines | K116: Laser Printer | L116: 7 | M116: 643.74 | N116: 0.15 | O116: 4506.18 | P116: -414.94
A117: ORD-10009 | B117: 45109 | C117: 45114 | D117: First Class | E117: Kamran Butt | F117: Corporate | G117: NORTH | H117: Rawalpindi | I117: Technology | J117: Machines | K117: Laser Printer | L117: 9 | M117: 858.38 | N117: 0.15 | O117: 7725.42 | P117: 2389.06
A118: ORD-10568 | B118: 45297 | C118: 45302 | D118: Standard Class | E118: Sana Raza | F118: Home Office | G118: north | H118: Lahore | I118: Office Supplies | J118: Art | K118: Highlighter Pack | L118: 1 | M118: 355.71 | N118: 0 | O118: 355.71 | P118: -38.81
A119: ORD-10053 | B119: 44960 | C119: 44962 | D119: Same Day | E119: Usman Chaudhry | F119: Consumer | G119: EAST | H119: Gujranwala | I119: Technology | J119: Copiers | K119: Desktop Copier | L119: 11 | M119: 532.86 | N119: 0.3 | O119: 5861.46 | P119: 1857.11
A120: ORD-10897 | B120: 45142 | C120: 45147 | D120: Same Day | E120: Hassan Qureshi | F120: Home Office | G120: SOUTH | H120: Karachi | I120: Furniture | J120: Furnishings | K120: Desk Lamp | L120: 11 | M120: 145.63 | N120: 0.15 | O120: 1601.93 | P120: 545.58
A121: ORD-10528 | B121: 45235 | C121: 45242 | D121: Same Day | E121: Hassan Butt | F121: Home Office | G121: west | H121: Peshawar | I121: Office Supplies | J121: Binders | K121: 3-Ring Binder | L121: 12 | M121: 633.83 | N121: 0.1 | O121: 7605.96 | P121: 652.17
A122: ORD-10431 | B122: 45480 | C122: 45486 | D122: Same Day | E122: Ali Raza | F122: Home Office | G122: east | I122: Furniture | J122: Chairs | K122: Folding Chair | L122: 12 | M122: 43.32 | N122: 0 | O122: 519.84 | P122: -22.96
A123: ORD-10305 | B123: 45069 | C123: 45073 | D123: Second Class | E123: Bilal Butt | F123: Corporate | G123: south | H123: Karachi | I123: Technology | J123: Accessories | K123: USB Cable | L123: 3 | M123: 329.19 | N123: 0.2 | O123: 987.57 | P123: 255.26
A124: ORD-10746 | B124: 45370 | C124: 45371 | D124: Second Class | E124: Ali Qureshi | F124: Home Office | G124: north | H124: Lahore | I124: Furniture | J124: Chairs | K124: Executive Leather Chair | L124: 5 | M124: 218.7 | N124: 0.15 | O124: 1093.5 | P124: -108.79
A125: ORD-10040 | B125: 45592 | C125: 45593 | D125: Same Day | E125: Usman Butt | F125: Home Office | G125: North | H125: Lahore | I125: Furniture | J125: Chairs | K125: Mesh Task Chair | L125: 8 | M125: 604.17 | N125: 0.15 | O125: 4833.36 | P125: 1565.42
...

Sheet Cleaning_Formulas
A2: Excel-Level Cleaning Formulas (initial pass, before SQL)
A3: These formulas reference Raw_Data directly and demonstrate TRIM(), PROPER(), and IFERROR() usage. Full/reliable cleaning is done later in SQL — this is the Excel-stage quality pass.
A5: Order ID | B5: Customer Name (Raw) | C5: Customer Name — TRIM+PROPER | D5: Discount (Raw) | E5: Discount — Validated (IFERROR) | F5: Sales — Validated (IFERROR)
A6: ORD-10216 | B6: IMRAN KHAN | C6: =IF(OR(B6="",B6=0), "Unknown Customer", PROPER(TRIM(B6))) -> Imran Khan | D6: 0 | E6: =IFERROR(IF(Raw_Data!N2="", 0, IF(Raw_Data!N2>1, Raw_Data!N2/100, Raw_Data!N2)), 0) -> 0 | F6: =IFERROR(VALUE(Raw_Data!O2), Raw_Data!L2*Raw_Data!M2) -> 1925.79
A7: ORD-11062 | B7: Fatima Raza | C7: =IF(OR(B7="",B7=0), "Unknown Customer", PROPER(TRIM(B7))) -> Fatima Raza | D7: 0 | E7: =IFERROR(IF(Raw_Data!N3="", 0, IF(Raw_Data!N3>1, Raw_Data!N3/100, Raw_Data!N3)), 0) -> 0 | F7: =IFERROR(VALUE(Raw_Data!O3), Raw_Data!L3*Raw_Data!M3) -> 2205.42
A8: ORD-11190 | B8: Zara Iqbal | C8: =IF(OR(B8="",B8=0), "Unknown Customer", PROPER(TRIM(B8))) -> Zara Iqbal | D8: 0 | E8: =IFERROR(IF(Raw_Data!N4="", 0, IF(Raw_Data!N4>1, Raw_Data!N4/100, Raw_Data!N4)), 0) -> 0 | F8: =IFERROR(VALUE(Raw_Data!O4), Raw_Data!L4*Raw_Data!M4) -> 1395.5
A9: ORD-10669 | B9: Hina Sheikh | C9: =IF(OR(B9="",B9=0), "Unknown Customer", PROPER(TRIM(B9))) -> Hina Sheikh | D9: 0.15 | E9: =IFERROR(IF(Raw_Data!N5="", 0, IF(Raw_Data!N5>1, Raw_Data!N5/100, Raw_Data!N5)), 0) -> 0.15 | F9: =IFERROR(VALUE(Raw_Data!O5), Raw_Data!L5*Raw_Data!M5) -> 2137.45
A10: ORD-10840 | B10: 0 | C10: =IF(OR(B10="",B10=0), "Unknown Customer", PROPER(TRIM(B10))) -> Unknown Customer | D10: 0.2 | E10: =IFERROR(IF(Raw_Data!N6="", 0, IF(Raw_Data!N6>1, Raw_Data!N6/100, Raw_Data!N6)), 0) -> 0.2 | F10: =IFERROR(VALUE(Raw_Data!O6), Raw_Data!L6*Raw_Data!M6) -> 896.19
A11: ORD-11011 | B11: Omar Raza | C11: =IF(OR(B11="",B11=0), "Unknown Customer", PROPER(TRIM(B11))) -> Omar Raza | D11: 0 | E11: =IFERROR(IF(Raw_Data!N7="", 0, IF(Raw_Data!N7>1, Raw_Data!N7/100, Raw_Data!N7)), 0) -> 0 | F11: =IFERROR(VALUE(Raw_Data!O7), Raw_Data!L7*Raw_Data!M7) -> 6820.6
A12: ORD-10492 | B12: Zara Qureshi | C12: =IF(OR(B12="",B12=0), "Unknown Customer", PROPER(TRIM(B12))) -> Zara Qureshi | D12: 0.3 | E12: =IFERROR(IF(Raw_Data!N8="", 0, IF(Raw_Data!N8>1, Raw_Data!N8/100, Raw_Data!N8)), 0) -> 0.3 | F12: =IFERROR(VALUE(Raw_Data!O8), Raw_Data!L8*Raw_Data!M8) -> 3695.76
A13: ORD-10172 | B13: Imran Sheikh | C13: =IF(OR(B13="",B13=0), "Unknown Customer", PROPER(TRIM(B13))) -> Imran Sheikh | D13: 0.1 | E13: =IFERROR(IF(Raw_Data!N9="", 0, IF(Raw_Data!N9>1, Raw_Data!N9/100, Raw_Data!N9)), 0) -> 0.1 | F13: =IFERROR(VALUE(Raw_Data!O9), Raw_Data!L9*Raw_Data!M9) -> 2999.82
A14: ORD-10063 | B14: Usman Qureshi | C14: =IF(OR(B14="",B14=0), "Unknown Customer", PROPER(TRIM(B14))) -> Usman Qureshi | D14: 0.3 | E14: =IFERROR(IF(Raw_Data!N10="", 0, IF(Raw_Data!N10>1, Raw_Data!N10/100, Raw_Data!N10)), 0) -> 0.3 | F14: =IFERROR(VALUE(Raw_Data!O10), Raw_Data!L10*Raw_Data!M10) -> 1498.28
A15: ORD-10681 | B15: Nida Khan | C15: =IF(OR(B15="",B15=0), "Unknown Customer", PROPER(TRIM(B15))) -> Nida Khan | D15: 0.3 | E15: =IFERROR(IF(Raw_Data!N11="", 0, IF(Raw_Data!N11>1, Raw_Data!N11/100, Raw_Data!N11)), 0) -> 0.3 | F15: =IFERROR(VALUE(Raw_Data!O11), Raw_Data!L11*Raw_Data!M11) -> 1489.54
A16: ORD-10051 | B16: Mahnoor Iqbal | C16: =IF(OR(B16="",B16=0), "Unknown Customer", PROPER(TRIM(B16))) -> Mahnoor Iqbal | D16: 0 | E16: =IFERROR(IF(Raw_Data!N12="", 0, IF(Raw_Data!N12>1, Raw_Data!N12/100, Raw_Data!N12)), 0) -> 0 | F16: =IFERROR(VALUE(Raw_Data!O12), Raw_Data!L12*Raw_Data!M12) -> 2569.6
A17: ORD-10650 | B17: Zara Butt | C17: =IF(OR(B17="",B17=0), "Unknown Customer", PROPER(TRIM(B17))) -> Zara Butt | D17: 0 | E17: =IFERROR(IF(Raw_Data!N13="", 0, IF(Raw_Data!N13>1, Raw_Data!N13/100, Raw_Data!N13)), 0) -> 0 | F17: =IFERROR(VALUE(Raw_Data!O13), Raw_Data!L13*Raw_Data!M13) -> 999.64
A18: ORD-11127 | B18: Ahmed Malik | C18: =IF(OR(B18="",B18=0), "Unknown Customer", PROPER(TRIM(B18))) -> Ahmed Malik | D18: 0 | E18: =IFERROR(IF(Raw_Data!N14="", 0, IF(Raw_Data!N14>1, Raw_Data!N14/100, Raw_Data!N14)), 0) -> 0 | F18: =IFERROR(VALUE(Raw_Data!O14), Raw_Data!L14*Raw_Data!M14) -> 1021.64
A19: ORD-10677 | B19: Hina Khan | C19: =IF(OR(B19="",B19=0), "Unknown Customer", PROPER(TRIM(B19))) -> Hina Khan | D19: 0.3 | E19: =IFERROR(IF(Raw_Data!N15="", 0, IF(Raw_Data!N15>1, Raw_Data!N15/100, Raw_Data!N15)), 0) -> 0.3 | F19: =IFERROR(VALUE(Raw_Data!O15), Raw_Data!L15*Raw_Data!M15) -> 8087.75
A20: ORD-10170 | B20: Fatima Qureshi | C20: =IF(OR(B20="",B20=0), "Unknown Customer", PROPER(TRIM(B20))) -> Fatima Qureshi | D20: 0.2 | E20: =IFERROR(IF(Raw_Data!N16="", 0, IF(Raw_Data!N16>1, Raw_Data!N16/100, Raw_Data!N16)), 0) -> 0.2 | F20: =IFERROR(VALUE(Raw_Data!O16), Raw_Data!L16*Raw_Data!M16) -> 2034.81
A21: ORD-10374 | B21: Zara Butt | C21: =IF(OR(B21="",B21=0), "Unknown Customer", PROPER(TRIM(B21))) -> Zara Butt | D21: 0 | E21: =IFERROR(IF(Raw_Data!N17="", 0, IF(Raw_Data!N17>1, Raw_Data!N17/100, Raw_Data!N17)), 0) -> 0 | F21: =IFERROR(VALUE(Raw_Data!O17), Raw_Data!L17*Raw_Data!M17) -> 402.24
A22: ORD-10395 | B22: Sana Ansari | C22: =IF(OR(B22="",B22=0), "Unknown Customer", PROPER(TRIM(B22))) -> Sana Ansari | D22: 0.15 | E22: =IFERROR(IF(Raw_Data!N18="", 0, IF(Raw_Data!N18>1, Raw_Data!N18/100, Raw_Data!N18)), 0) -> 0.15 | F22: =IFERROR(VALUE(Raw_Data!O18), Raw_Data!L18*Raw_Data!M18) -> 720.13
... A140: ORD-10407 | B140: Fatima Raza | C140: =IF(OR(B140="",B140=0), "Unknown Customer", PROPER(TRIM(B140))) -> Fatima Raza | D140: 0.2 | E140: =IFERROR(IF(Raw_Data!N136="", 0, IF(Raw_Data!N136>1, Raw_Data!N136/100, Raw_Data!N136)), 0) -> 0.2 | F140: =IFERROR(VALUE(Raw_Data!O136), Raw_Data!L136*Raw_Data!M136) -> 2577
B141: 0 | C141: =IF(OR(B141="",B141=0), "Unknown Customer", PROPER(TRIM(B141))) -> Unknown Customer | D141: 0 | E141: =IFERROR(IF(Raw_Data!N137="", 0, IF(Raw_Data!N137>1, Raw_Data!N137/100, Raw_Data!N137)), 0) -> 0 | F141: =IFERROR(VALUE(Raw_Data!O137), Raw_Data!L137*Raw_Data!M137) -> 0
B142: Rabia Chaudhry | C142: =IF(OR(B142="",B142=0), "Unknown Customer", PROPER(TRIM(B142))) -> Rabia Chaudhry | D142: 0 | E142: =IFERROR(IF(Raw_Data!N138="", 0, IF(Raw_Data!N138>1, Raw_Data!N138/100, Raw_Data!N138)), 0) -> 0 | F142: =IFERROR(VALUE(Raw_Data!O138), Raw_Data!L138*Raw_Data!M138) -> 521.92
B143: Faisal Sheikh | C143: =IF(OR(B143="",B143=0), "Unknown Customer", PROPER(TRIM(B143))) -> Faisal Sheikh | D143: 0.15 | E143: =IFERROR(IF(Raw_Data!N139="", 0, IF(Raw_Data!N139>1, Raw_Data!N139/100, Raw_Data!N139)), 0) -> 0.15 | F143: =IFERROR(VALUE(Raw_Data!O139), Raw_Data!L139*Raw_Data!M139) -> 245.9
B144: Ahmed Qureshi | C144: =IF(OR(B144="",B144=0), "Unknown Customer", PROPER(TRIM(B144))) -> Ahmed Qureshi | D144: 0 | E144: =IFERROR(IF(Raw_Data!N140="", 0, IF(Raw_Data!N140>1, Raw_Data!N140/100, Raw_Data!N140)), 0) -> 0 | F144: =IFERROR(VALUE(Raw_Data!O140), Raw_Data!L140*Raw_Data!M140) -> 345.56
B145: Ali Qureshi | C145: =IF(OR(B145="",B145=0), "Unknown Customer", PROPER(TRIM(B145))) -> Ali Qureshi | D145: 0.3 | E145: =IFERROR(IF(Raw_Data!N141="", 0, IF(Raw_Data!N141>1, Raw_Data!N141/100, Raw_Data!N141)), 0) -> 0.3 | F145: =IFERROR(VALUE(Raw_Data!O141), Raw_Data!L141*Raw_Data!M141) -> 1066.72
B146: Ayesha Qureshi | C146: =IF(OR(B146="",B146=0), "Unknown Customer", PROPER(TRIM(B146))) -> Ayesha Qureshi | D146: 0 | E146: =IFERROR(IF(Raw_Data!N142="", 0, IF(Raw_Data!N142>1, Raw_Data!N142/100, Raw_Data!N142)), 0) -> 0 | F146: =IFERROR(VALUE(Raw_Data!O142), Raw_Data!L142*Raw_Data!M142) -> 2123.6
B147: Ayesha Butt | C147: =IF(OR(B147="",B147=0), "Unknown Customer", PROPER(TRIM(B147))) -> Ayesha Butt | D147: 0 | E147: =IFERROR(IF(Raw_Data!N143="", 0, IF(Raw_Data!N143>1, Raw_Data!N143/100, Raw_Data!N143)), 0) -> 0 | F147: =IFERROR(VALUE(Raw_Data!O143), Raw_Data!L143*Raw_Data!M143) -> 1296.96
B148: Tariq Butt | C148: =IF(OR(B148="",B148=0), "Unknown Customer", PROPER(TRIM(B148))) -> Tariq Butt | D148: 0.15 | E148: =IFERROR(IF(Raw_Data!N144="", 0, IF(Raw_Data!N144>1, Raw_Data!N144/100, Raw_Data!N144)), 0) -> 0.15 | F148: =IFERROR(VALUE(Raw_Data!O144), Raw_Data!L144*Raw_Data!M144) -> 2355.84
B149: Tariq Malik | C149: =IF(OR(B149="",B149=0), "Unknown Customer", PROPER(TRIM(B149))) -> Tariq Malik | D149: 0.15 | E149: =IFERROR(IF(Raw_Data!N145="", 0, IF(Raw_Data!N145>1, Raw_Data!N145/100, Raw_Data!N145)), 0) -> 0.15 | F149: =IFERROR(VALUE(Raw_Data!O145), Raw_Data!L145*Raw_Data!M145) -> 5208.12
B150: Omar Qureshi | C150: =IF(OR(B150="",B150=0), "Unknown Customer", PROPER(TRIM(B150))) -> Omar Qureshi | D150: 0 | E150: =IFERROR(IF(Raw_Data!N146="", 0, IF(Raw_Data!N146>1, Raw_Data!N146/100, Raw_Data!N146)), 0) -> 0 | F150: =IFERROR(VALUE(Raw_Data!O146), Raw_Data!L146*Raw_Data!M146) -> 8912.4
B151: Ali Iqbal | C151: =IF(OR(B151="",B151=0), "Unknown Customer", PROPER(TRIM(B151))) -> Ali Iqbal | D151: 0.1 | E151: =IFERROR(IF(Raw_Data!N147="", 0, IF(Raw_Data!N147>1, Raw_Data!N147/100, Raw_Data!N147)), 0) -> 0.1 | F151: =IFERROR(VALUE(Raw_Data!O147), Raw_Data!L147*Raw_Data!M147) -> 4969.5
B152: Bilal Iqbal | C152: =IF(OR(B152="",B152=0), "Unknown Customer", PROPER(TRIM(B152))) -> Bilal Iqbal | D152: 0 | E152: =IFERROR(IF(Raw_Data!N148="", 0, IF(Raw_Data!N148>1, Raw_Data!N148/100, Raw_Data!N148)), 0) -> 0 | F152: =IFERROR(VALUE(Raw_Data!O148), Raw_Data!L148*Raw_Data!M148) -> 827.31
B153: Hina Butt | C153: =IF(OR(B153="",B153=0), "Unknown Customer", PROPER(TRIM(B153))) -> Hina Butt | D153: 0.1 | E153: =IFERROR(IF(Raw_Data!N149="", 0, IF(Raw_Data!N149>1, Raw_Data!N149/100, Raw_Data!N149)), 0) -> 0.1 | F153: =IFERROR(VALUE(Raw_Data!O149), Raw_Data!L149*Raw_Data!M149) -> 8087.4
... B172: Imran Butt | C172: =IF(OR(B172="",B172=0), "Unknown Customer", PROPER(TRIM(B172))) -> Imran Butt | D172: 0.1 | E172: =IFERROR(IF(Raw_Data!N168="", 0, IF(Raw_Data!N168>1, Raw_Data!N168/100, Raw_Data!N168)), 0) -> 0.1 | F172: =IFERROR(VALUE(Raw_Data!O168), Raw_Data!L168*Raw_Data!M168) -> 191.04
B173: 0 | C173: =IF(OR(B173="",B173=0), "Unknown Customer", PROPER(TRIM(B173))) -> Unknown Customer | D173: 0 | E173: =IFERROR(IF(Raw_Data!N169="", 0, IF(Raw_Data!N169>1, Raw_Data!N169/100, Raw_Data!N169)), 0) -> 0 | F173: =IFERROR(VALUE(Raw_Data!O169), Raw_Data!L169*Raw_Data!M169) -> 5378.72
B174: Usman Farooq | C174: =IF(OR(B174="",B174=0), "Unknown Customer", PROPER(TRIM(B174))) -> Usman Farooq | D174: 0.3 | E174: =IFERROR(IF(Raw_Data!N170="", 0, IF(Raw_Data!N170>1, Raw_Data!N170/100, Raw_Data!N170)), 0) -> 0.3 | F174: =IFERROR(VALUE(Raw_Data!O170), Raw_Data!L170*Raw_Data!M170) -> 2255.22
B175: Rabia Khan | C175: =IF(OR(B175="",B175=0), "Unknown Customer", PROPER(TRIM(B175))) -> Rabia Khan | D175: 0 | E175: =IFERROR(IF(Raw_Data!N171="", 0, IF(Raw_Data!N171>1, Raw_Data!N171/100, Raw_Data!N171)), 0) -> 0 | F175: =IFERROR(VALUE(Raw_Data!O171), Raw_Data!L171*Raw_Data!M171) -> 8099.41
B176: Usman Farooq | C176: =IF(OR(B176="",B176=0), "Unknown Customer", PROPER(TRIM(B176))) -> Usman Farooq | D176: 0.2 | E176: =IFERROR(IF(Raw_Data!N172="", 0, IF(Raw_Data!N172>1, Raw_Data!N172/100, Raw_Data!N172)), 0) -> 0.2 | F176: =IFERROR(VALUE(Raw_Data!O172), Raw_Data!L172*Raw_Data!M172) -> 5382.48
B177: Sana Chaudhry | C177: =IF(OR(B177="",B177=0), "Unknown Customer", PROPER(TRIM(B177))) -> Sana Chaudhry | D177: 0.2 | E177: =IFERROR(IF(Raw_Data!N173="", 0, IF(Raw_Data!N173>1, Raw_Data!N173/100, Raw_Data!N173)), 0) -> 0.2 | F177: =IFERROR(VALUE(Raw_Data!O173), Raw_Data!L173*Raw_Data!M173) -> 475.09
B178: Ahmed Malik | C178: =IF(OR(B178="",B178=0), "Unknown Customer", PROPER(TRIM(B178))) -> Ahmed Malik | D178: 0.2 | E178: =IFERROR(IF(Raw_Data!N174="", 0, IF(Raw_Data!N174>1, Raw_Data!N174/100, Raw_Data!N174)), 0) -> 0.2 | F178: =IFERROR(VALUE(Raw_Data!O174), Raw_Data!L174*Raw_Data!M174) -> 915.66
B179: Adeel Ansari | C179: =IF(OR(B179="",B179=0), "Unknown Customer", PROPER(TRIM(B179))) -> Adeel Ansari | D179: 0 | E179: =IFERROR(IF(Raw_Data!N175="", 0, IF(Raw_Data!N175>1, Raw_Data!N175/100, Raw_Data!N175)), 0) -> 0 | F179: =IFERROR(VALUE(Raw_Data!O175), Raw_Data!L175*Raw_Data!M175) -> 6171.84
B180: Fatima Malik | C180: =IF(OR(B180="",B180=0), "Unknown Customer", PROPER(TRIM(B180))) -> Fatima Malik | D180: 0 | E180: =IFERROR(IF(Raw_Data!N176="", 0, IF(Raw_Data!N176>1, Raw_Data!N176/100, Raw_Data!N176)), 0) -> 0 | F180: =IFERROR(VALUE(Raw_Data!O176), Raw_Data!L176*Raw_Data!M176) -> 6863.22
B181: Ali Khan | C181: =IF(OR(B181="",B181=0), "Unknown Customer", PROPER(TRIM(B181))) -> Ali Khan | D181: 0.15 | E181: =IFERROR(IF(Raw_Data!N177="", 0, IF(Raw_Data!N177>1, Raw_Data!N177/100, Raw_Data!N177)), 0) -> 0.15 | F181: =IFERROR(VALUE(Raw_Data!O177), Raw_Data!L177*Raw_Data!M177) -> 5291.68
B182: Sara Iqbal | C182: =IF(OR(B182="",B182=0), "Unknown Customer", PROPER(TRIM(B182))) -> Sara Iqbal | D182: 0.2 | E182: =IFERROR(IF(Raw_Data!N178="", 0, IF(Raw_Data!N178>1, Raw_Data!N178/100, Raw_Data!N178)), 0) -> 0.2 | F182: =IFERROR(VALUE(Raw_Data!O178), Raw_Data!L178*Raw_Data!M178) -> 2231.04
B183: Hassan Farooq | C183: =IF(OR(B183="",B183=0), "Unknown Customer", PROPER(TRIM(B183))) -> Hassan Farooq | D183: 0 | E183: =IFERROR(IF(Raw_Data!N179="", 0, IF(Raw_Data!N179>1, Raw_Data!N179/100, Raw_Data!N179)), 0) -> 0 | F183: =IFERROR(VALUE(Raw_Data!O179), Raw_Data!L179*Raw_Data!M179) -> 85.78
B184: Mahnoor Malik | C184: =IF(OR(B184="",B184=0), "Unknown Customer", PROPER(TRIM(B184))) -> Mahnoor Malik | D184: 0.15 | E184: =IFERROR(IF(Raw_Data!N180="", 0, IF(Raw_Data!N180>1, Raw_Data!N180/100, Raw_Data!N180)), 0) -> 0.15 | F184: =IFERROR(VALUE(Raw_Data!O180), Raw_Data!L180*Raw_Data!M180) -> 3314.88
B185: Bilal Iqbal | C185: =IF(OR(B185="",B185=0), "Unknown Customer", PROPER(TRIM(B185))) -> Bilal Iqbal | D185: 0 | E185: =IFERROR(IF(Raw_Data!N181="", 0, IF(Raw_Data!N181>1, Raw_Data!N181/100, Raw_Data!N181)), 0) -> 0 | F185: =IFERROR(VALUE(Raw_Data!O181), Raw_Data!L181*Raw_Data!M181) -> 3562.23
... B187: Rabia Malik | C187: =IF(OR(B187="",B187=0), "Unknown Customer", PROPER(TRIM(B187))) -> Rabia Malik | D187: 0 | E187: =IFERROR(IF(Raw_Data!N183="", 0, IF(Raw_Data!N183>1, Raw_Data!N183/100, Raw_Data!N183)), 0) -> 0 | F187: =IFERROR(VALUE(Raw_Data!O183), Raw_Data!L183*Raw_Data!M183) -> 198.99
B188: 0 | C188: =IF(OR(B188="",B188=0), "Unknown Customer", PROPER(TRIM(B188))) -> Unknown Customer | D188: 0 | E188: =IFERROR(IF(Raw_Data!N184="", 0, IF(Raw_Data!N184>1, Raw_Data!N184/100, Raw_Data!N184)), 0) -> 0 | F188: =IFERROR(VALUE(Raw_Data!O184), Raw_Data!L184*Raw_Data!M184) -> 1668.6
B189: Ahmed Chaudhry | C189: =IF(OR(B189="",B189=0), "Unknown Customer", PROPER(TRIM(B189))) -> Ahmed Chaudhry | D189: 0.15 | E189: =IFERROR(IF(Raw_Data!N185="", 0, IF(Raw_Data!N185>1, Raw_Data!N185/100, Raw_Data!N185)), 0) -> 0.15 | F189: =IFERROR(VALUE(Raw_Data!O185), Raw_Data!L185*Raw_Data!M185) -> 2770.96
B190: Nida Butt | C190: =IF(OR(B190="",B190=0), "Unknown Customer", PROPER(TRIM(B190))) -> Nida Butt | D190: 0.1 | E190: =IFERROR(IF(Raw_Data!N186="", 0, IF(Raw_Data!N186>1, Raw_Data!N186/100, Raw_Data!N186)), 0) -> 0.1 | F190: =IFERROR(VALUE(Raw_Data!O186), Raw_Data!L186*Raw_Data!M186) -> 4233.04
B191: Hassan Qureshi | C191: =IF(OR(B191="",B191=0), "Unknown Customer", PROPER(TRIM(B191))) -> Hassan Qureshi | D191: 0.3 | E191: =IFERROR(IF(Raw_Data!N187="", 0, IF(Raw_Data!N187>1, Raw_Data!N187/100, Raw_Data!N187)), 0) -> 0.3 | F191: =IFERROR(VALUE(Raw_Data!O187), Raw_Data!L187*Raw_Data!M187) -> 2784.78
B192: Fatima Butt | C192: =IF(OR(B192="",B192=0), "Unknown Customer", PROPER(TRIM(B192))) -> Fatima Butt | D192: 0 | E192: =IFERROR(IF(Raw_Data!N188="", 0, IF(Raw_Data!N188>1, Raw_Data!N188/100, Raw_Data!N188)), 0) -> 0 | F192: =IFERROR(VALUE(Raw_Data!O188), Raw_Data!L188*Raw_Data!M188) -> 1753.44
B193: Tariq Qureshi | C193: =IF(OR(B193="",B193=0), "Unknown Customer", PROPER(TRIM(B193))) -> Tariq Qureshi | D193: 0.15 | E193: =IFERROR(IF(Raw_Data!N189="", 0, IF(Raw_Data!N189>1, Raw_Data!N189/100, Raw_Data!N189)), 0) -> 0.15 | F193: =IFERROR(VALUE(Raw_Data!O189), Raw_Data!L189*Raw_Data!M189) -> 7201
B194: Rabia Chaudhry | C194: =IF(OR(B194="",B194=0), "Unknown Customer", PROPER(TRIM(B194))) -> Rabia Chaudhry | D194: 0 | E194: =IFERROR(IF(Raw_Data!N190="", 0, IF(Raw_Data!N190>1, Raw_Data!N190/100, Raw_Data!N190)), 0) -> 0 | F194: =IFERROR(VALUE(Raw_Data!O190), Raw_Data!L190*Raw_Data!M190) -> 1311.48
B195: Rabia Malik | C195: =IF(OR(B195="",B195=0), "Unknown Customer", PROPER(TRIM(B195))) -> Rabia Malik | D195: 0.15 | E195: =IFERROR(IF(Raw_Data!N191="", 0, IF(Raw_Data!N191>1, Raw_Data!N191/100, Raw_Data!N191)), 0) -> 0.15 | F195: =IFERROR(VALUE(Raw_Data!O191), Raw_Data!L191*Raw_Data!M191) -> 1152.95
B196: Nida Khan | C196: =IF(OR(B196="",B196=0), "Unknown Customer", PROPER(TRIM(B196))) -> Nida Khan | D196: 0 | E196: =IFERROR(IF(Raw_Data!N192="", 0, IF(Raw_Data!N192>1, Raw_Data!N192/100, Raw_Data!N192)), 0) -> 0 | F196: =IFERROR(VALUE(Raw_Data!O192), Raw_Data!L192*Raw_Data!M192) -> 2265.1
B197: Adeel Malik | C197: =IF(OR(B197="",B197=0), "Unknown Customer", PROPER(TRIM(B197))) -> Adeel Malik | D197: 0 | E197: =IFERROR(IF(Raw_Data!N193="", 0, IF(Raw_Data!N193>1, Raw_Data!N193/100, Raw_Data!N193)), 0) -> 0 | F197: =IFERROR(VALUE(Raw_Data!O193), Raw_Data!L193*Raw_Data!M193) -> 5162.24
B198: Ahmed Iqbal | C198: =IF(OR(B198="",B198=0), "Unknown Customer", PROPER(TRIM(B198))) -> Ahmed Iqbal | D198: 0 | E198: =IFERROR(IF(Raw_Data!N194="", 0, IF(Raw_Data!N194>1, Raw_Data!N194/100, Raw_Data!N194)), 0) -> 0 | F198: =IFERROR(VALUE(Raw_Data!O194), Raw_Data!L194*Raw_Data!M194) -> 2876.9
B199: Hassan Farooq | C199: =IF(OR(B199="",B199=0), "Unknown Customer", PROPER(TRIM(B199))) -> Hassan Farooq | D199: 0 | E199: =IFERROR(IF(Raw_Data!N195="", 0, IF(Raw_Data!N195>1, Raw_Data!N195/100, Raw_Data!N195)), 0) -> 0 | F199: =IFERROR(VALUE(Raw_Data!O195), Raw_Data!L195*Raw_Data!M195) -> 4055.52
B200: Ali Iqbal | C200: =IF(OR(B200="",B200=0), "Unknown Customer", PROPER(TRIM(B200))) -> Ali Iqbal | D200: 0.15 | E200: =IFERROR(IF(Raw_Data!N196="", 0, IF(Raw_Data!N196>1, Raw_Data!N196/100, Raw_Data!N196)), 0) -> 0.15 | F200: =IFERROR(VALUE(Raw_Data!O196), Raw_Data!L196*Raw_Data!M196) -> 2573.23
... B347: Hassan Malik | C347: =IF(OR(B347="",B347=0), "Unknown Customer", PROPER(TRIM(B347))) -> Hassan Malik | D347: 0.3 | E347: =IFERROR(IF(Raw_Data!N343="", 0, IF(Raw_Data!N343>1, Raw_Data!N343/100, Raw_Data!N343)), 0) -> 0.3 | F347: =IFERROR(VALUE(Raw_Data!O343), Raw_Data!L343*Raw_Data!M343) -> 2612.32
B348: 0 | C348: =IF(OR(B348="",B348=0), "Unknown Customer", PROPER(TRIM(B348))) -> Unknown Customer | D348: 0.15 | E348: =IFERROR(IF(Raw_Data!N344="", 0, IF(Raw_Data!N344>1, Raw_Data!N344/100, Raw_Data!N344)), 0) -> 0.15 | F348: =IFERROR(VALUE(Raw_Data!O344), Raw_Data!L344*Raw_Data!M344) -> 480.68
B349: Sara Iqbal | C349: =IF(OR(B349="",B349=0), "Unknown Customer", PROPER(TRIM(B349))) -> Sara Iqbal | D349: 0.2 | E349: =IFERROR(IF(Raw_Data!N345="", 0, IF(Raw_Data!N345>1, Raw_Data!N345/100, Raw_Data!N345)), 0) -> 0.2 | F349: =IFERROR(VALUE(Raw_Data!O345), Raw_Data!L345*Raw_Data!M345) -> 6084.63
B350: Bilal Chaudhry | C350: =IF(OR(B350="",B350=0), "Unknown Customer", PROPER(TRIM(B350))) -> Bilal Chaudhry | D350: 0.3 | E350: =IFERROR(IF(Raw_Data!N346="", 0, IF(Raw_Data!N346>1, Raw_Data!N346/100, Raw_Data!N346)), 0) -> 0.3 | F350: =IFERROR(VALUE(Raw_Data!O346), Raw_Data!L346*Raw_Data!M346) -> 3486.12
B351: Tariq Khan | C351: =IF(OR(B351="",B351=0), "Unknown Customer", PROPER(TRIM(B351))) -> Tariq Khan | D351: 0 | E351: =IFERROR(IF(Raw_Data!N347="", 0, IF(Raw_Data!N347>1, Raw_Data!N347/100, Raw_Data!N347)), 0) -> 0 | F351: =IFERROR(VALUE(Raw_Data!O347), Raw_Data!L347*Raw_Data!M347) -> 1655.4
B352: Hina Butt | C352: =IF(OR(B352="",B352=0), "Unknown Customer", PROPER(TRIM(B352))) -> Hina Butt | D352: 0.3 | E352: =IFERROR(IF(Raw_Data!N348="", 0, IF(Raw_Data!N348>1, Raw_Data!N348/100, Raw_Data!N348)), 0) -> 0.3 | F352: =IFERROR(VALUE(Raw_Data!O348), Raw_Data!L348*Raw_Data!M348) -> 2833.53
B353: Kamran Ansari | C353: =IF(OR(B353="",B353=0), "Unknown Customer", PROPER(TRIM(B353))) -> Kamran Ansari | D353: 0.3 | E353: =IFERROR(IF(Raw_Data!N349="", 0, IF(Raw_Data!N349>1, Raw_Data!N349/100, Raw_Data!N349)), 0) -> 0.3 | F353: =IFERROR(VALUE(Raw_Data!O349), Raw_Data!L349*Raw_Data!M349) -> 4292.19
B354: Imran Qureshi | C354: =IF(OR(B354="",B354=0), "Unknown Customer", PROPER(TRIM(B354))) -> Imran Qureshi | D354: 0 | E354: =IFERROR(IF(Raw_Data!N350="", 0, IF(Raw_Data!N350>1, Raw_Data!N350/100, Raw_Data!N350)), 0) -> 0 | F354: =IFERROR(VALUE(Raw_Data!O350), Raw_Data!L350*Raw_Data!M350) -> 689
B355: Ayesha Iqbal | C355: =IF(OR(B355="",B355=0), "Unknown Customer", PROPER(TRIM(B355))) -> Ayesha Iqbal | D355: 0 | E355: =IFERROR(IF(Raw_Data!N351="", 0, IF(Raw_Data!N351>1, Raw_Data!N351/100, Raw_Data!N351)), 0) -> 0 | F355: =IFERROR(VALUE(Raw_Data!O351), Raw_Data!L351*Raw_Data!M351) -> 3292.68
B356: Sana Ansari | C356: =IF(OR(B356="",B356=0), "Unknown Customer", PROPER(TRIM(B356))) -> Sana Ansari | D356: 0.1 | E356: =IFERROR(IF(Raw_Data!N352="", 0, IF(Raw_Data!N352>1, Raw_Data!N352/100, Raw_Data!N352)), 0) -> 0.1 | F356: =IFERROR(VALUE(Raw_Data!O352), Raw_Data!L352*Raw_Data!M352) -> 4891.12
B357: Rabia Iqbal | C357: =IF(OR(B357="",B357=0), "Unknown Customer", PROPER(TRIM(B357))) -> Rabia Iqbal | D357: 0.3 | E357: =IFERROR(IF(Raw_Data!N353="", 0, IF(Raw_Data!N353>1, Raw_Data!N353/100, Raw_Data!N353)), 0) -> 0.3 | F357: =IFERROR(VALUE(Raw_Data!O353), Raw_Data!L353*Raw_Data!M353) -> 392.64
B358: Mahnoor Khan | C358: =IF(OR(B358="",B358=0), "Unknown Customer", PROPER(TRIM(B358))) -> Mahnoor Khan | D358: 0 | E358: =IFERROR(IF(Raw_Data!N354="", 0, IF(Raw_Data!N354>1, Raw_Data!N354/100, Raw_Data!N354)), 0) -> 0 | F358: =IFERROR(VALUE(Raw_Data!O354), Raw_Data!L354*Raw_Data!M354) -> 931.53
B359: Bilal Iqbal | C359: =IF(OR(B359="",B359=0), "Unknown Customer", PROPER(TRIM(B359))) -> Bilal Iqbal | D359: 0.15 | E359: =IFERROR(IF(Raw_Data!N355="", 0, IF(Raw_Data!N355>1, Raw_Data!N355/100, Raw_Data!N355)), 0) -> 0.15 | F359: =IFERROR(VALUE(Raw_Data!O355), Raw_Data!L355*Raw_Data!M355) -> 3320.28
B360: Sara Raza | C360: =IF(OR(B360="",B360=0), "Unknown Customer", PROPER(TRIM(B360))) -> Sara Raza | D360: 0 | E360: =IFERROR(IF(Raw_Data!N356="", 0, IF(Raw_Data!N356>1, Raw_Data!N356/100, Raw_Data!N356)), 0) -> 0 | F360: =IFERROR(VALUE(Raw_Data!O356), Raw_Data!L356*Raw_Data!M356) -> 1127.32
... B433: Mahnoor Chaudhry | C433: =IF(OR(B433="",B433=0), "Unknown Customer", PROPER(TRIM(B433))) -> Mahnoor Chaudhry | D433: 0.3 | E433: =IFERROR(IF(Raw_Data!N429="", 0, IF(Raw_Data!N429>1, Raw_Data!N429/100, Raw_Data!N429)), 0) -> 0.3 | F433: =IFERROR(VALUE(Raw_Data!O429), Raw_Data!L429*Raw_Data!M429) -> 2337.24
B434: 0 | C434: =IF(OR(B434="",B434=0), "Unknown Customer", PROPER(TRIM(B434))) -> Unknown Customer | D434: 0 | E434: =IFERROR(IF(Raw_Data!N430="", 0, IF(Raw_Data!N430>1, Raw_Data!N430/100, Raw_Data!N430)), 0) -> 0 | F434: =IFERROR(VALUE(Raw_Data!O430), Raw_Data!L430*Raw_Data!M430) -> 2574.56
B435: Rabia Qureshi | C435: =IF(OR(B435="",B435=0), "Unknown Customer", PROPER(TRIM(B435))) -> Rabia Qureshi | D435: 0.2 | E435: =IFERROR(IF(Raw_Data!N431="", 0, IF(Raw_Data!N431>1, Raw_Data!N431/100, Raw_Data!N431)), 0) -> 0.2 | F435: =IFERROR(VALUE(Raw_Data!O431), Raw_Data!L431*Raw_Data!M431) -> 6289.36
B436: Zara Khan | C436: =IF(OR(B436="",B436=0), "Unknown Customer", PROPER(TRIM(B436))) -> Zara Khan | D436: 0 | E436: =IFERROR(IF(Raw_Data!N432="", 0, IF(Raw_Data!N432>1, Raw_Data!N432/100, Raw_Data!N432)), 0) -> 0 | F436: =IFERROR(VALUE(Raw_Data!O432), Raw_Data!L432*Raw_Data!M432) -> 1891.35
B437: Sara Khan | C437: =IF(OR(B437="",B437=0), "Unknown Customer", PROPER(TRIM(B437))) -> Sara Khan | D437: 0.3 | E437: =IFERROR(IF(Raw_Data!N433="", 0, IF(Raw_Data!N433>1, Raw_Data!N433/100, Raw_Data!N433)), 0) -> 0.3 | F437: =IFERROR(VALUE(Raw_Data!O433), Raw_Data!L433*Raw_Data!M433) -> 107.31
B438: Tariq Iqbal | C438: =IF(OR(B438="",B438=0), "Unknown Customer", PROPER(TRIM(B438))) -> Tariq Iqbal | D438: 0.1 | E438: =IFERROR(IF(Raw_Data!N434="", 0, IF(Raw_Data!N434>1, Raw_Data!N434/100, Raw_Data!N434)), 0) -> 0.1 | F438: =IFERROR(VALUE(Raw_Data!O434), Raw_Data!L434*Raw_Data!M434) -> 1700.08
B439: Nida Farooq | C439: =IF(OR(B439="",B439=0), "Unknown Customer", PROPER(TRIM(B439))) -> Nida Farooq | D439: 0 | E439: =IFERROR(IF(Raw_Data!N435="", 0, IF(Raw_Data!N435>1, Raw_Data!N435/100, Raw_Data!N435)), 0) -> 0 | F439: =IFERROR(VALUE(Raw_Data!O435), Raw_Data!L435*Raw_Data!M435) -> 742.35
B440: Hassan Khan | C440: =IF(OR(B440="",B440=0), "Unknown Customer", PROPER(TRIM(B440))) -> Hassan Khan | D440: 0.15 | E440: =IFERROR(IF(Raw_Data!N436="", 0, IF(Raw_Data!N436>1, Raw_Data!N436/100, Raw_Data!N436)), 0) -> 0.15 | F440: =IFERROR(VALUE(Raw_Data!O436), Raw_Data!L436*Raw_Data!M436) -> 674.75
B441: Hassan Ansari | C441: =IF(OR(B441="",B441=0), "Unknown Customer", PROPER(TRIM(B441))) -> Hassan Ansari | D441: 0.1 | E441: =IFERROR(IF(Raw_Data!N437="", 0, IF(Raw_Data!N437>1, Raw_Data!N437/100, Raw_Data!N437)), 0) -> 0.1 | F441: =IFERROR(VALUE(Raw_Data!O437), Raw_Data!L437*Raw_Data!M437) -> 3141.2
B442: Faisal Farooq | C442: =IF(OR(B442="",B442=0), "Unknown Customer", PROPER(TRIM(B442))) -> Faisal Farooq | D442: 0 | E442: =IFERROR(IF(Raw_Data!N438="", 0, IF(Raw_Data!N438>1, Raw_Data!N438/100, Raw_Data!N438)), 0) -> 0 | F442: =IFERROR(VALUE(Raw_Data!O438), Raw_Data!L438*Raw_Data!M438) -> 9025.8
B443: Nida Malik | C443: =IF(OR(B443="",B443=0), "Unknown Customer", PROPER(TRIM(B443))) -> Nida Malik | D443: 0.1 | E443: =IFERROR(IF(Raw_Data!N439="", 0, IF(Raw_Data!N439>1, Raw_Data!N439/100, Raw_Data!N439)), 0) -> 0.1 | F443: =IFERROR(VALUE(Raw_Data!O439), Raw_Data!L439*Raw_Data!M439) -> 1409.84
B444: Nida Qureshi | C444: =IF(OR(B444="",B444=0), "Unknown Customer", PROPER(TRIM(B444))) -> Nida Qureshi | D444: 0.2 | E444: =IFERROR(IF(Raw_Data!N440="", 0, IF(Raw_Data!N440>1, Raw_Data!N440/100, Raw_Data!N440)), 0) -> 0.2 | F444: =IFERROR(VALUE(Raw_Data!O440), Raw_Data!L440*Raw_Data!M440) -> 6211.68
B445: Adeel Qureshi | C445: =IF(OR(B445="",B445=0), "Unknown Customer", PROPER(TRIM(B445))) -> Adeel Qureshi | D445: 0.2 | E445: =IFERROR(IF(Raw_Data!N441="", 0, IF(Raw_Data!N441>1, Raw_Data!N441/100, Raw_Data!N441)), 0) -> 0.2 | F445: =IFERROR(VALUE(Raw_Data!O441), Raw_Data!L441*Raw_Data!M441) -> 3738.84
B446: Hina Raza | C446: =IF(OR(B446="",B446=0), "Unknown Customer", PROPER(TRIM(B446))) -> Hina Raza | D446: 0 | E446: =IFERROR(IF(Raw_Data!N442="", 0, IF(Raw_Data!N442>1, Raw_Data!N442/100, Raw_Data!N442)), 0) -> 0 | F446: =IFERROR(VALUE(Raw_Data!O442), Raw_Data!L442*Raw_Data!M442) -> 1354.2
... B489: Rabia Butt | C489: =IF(OR(B489="",B489=0), "Unknown Customer", PROPER(TRIM(B489))) -> Rabia Butt | D489: 0 | E489: =IFERROR(IF(Raw_Data!N485="", 0, IF(Raw_Data!N485>1, Raw_Data!N485/100, Raw_Data!N485)), 0) -> 0 | F489: =IFERROR(VALUE(Raw_Data!O485), Raw_Data!L485*Raw_Data!M485) -> 54.4
B490: 0 | C490: =IF(OR(B490="",B490=0), "Unknown Customer", PROPER(TRIM(B490))) -> Unknown Customer | D490: 0 | E490: =IFERROR(IF(Raw_Data!N486="", 0, IF(Raw_Data!N486>1, Raw_Data!N486/100, Raw_Data!N486)), 0) -> 0 | F490: =IFERROR(VALUE(Raw_Data!O486), Raw_Data!L486*Raw_Data!M486) -> 5289.6
B491: Imran Iqbal | C491: =IF(OR(B491="",B491=0), "Unknown Customer", PROPER(TRIM(B491))) -> Imran Iqbal | D491: 0 | E491: =IFERROR(IF(Raw_Data!N487="", 0, IF(Raw_Data!N487>1, Raw_Data!N487/100, Raw_Data!N487)), 0) -> 0 | F491: =IFERROR(VALUE(Raw_Data!O487), Raw_Data!L487*Raw_Data!M487) -> 158.38
B492: Hina Farooq | C492: =IF(OR(B492="",B492=0), "Unknown Customer", PROPER(TRIM(B492))) -> Hina Farooq | D492: 0.3 | E492: =IFERROR(IF(Raw_Data!N488="", 0, IF(Raw_Data!N488>1, Raw_Data!N488/100, Raw_Data!N488)), 0) -> 0.3 | F492: =IFERROR(VALUE(Raw_Data!O488), Raw_Data!L488*Raw_Data!M488) -> 3228.8
B493: Omar Butt | C493: =IF(OR(B493="",B493=0), "Unknown Customer", PROPER(TRIM(B493))) -> Omar Butt | D493: 0 | E493: =IFERROR(IF(Raw_Data!N489="", 0, IF(Raw_Data!N489>1, Raw_Data!N489/100, Raw_Data!N489)), 0) -> 0 | F493: =IFERROR(VALUE(Raw_Data!O489), Raw_Data!L489*Raw_Data!M489) -> 1039.85
B494: Faisal Iqbal | C494: =IF(OR(B494="",B494=0), "Unknown Customer", PROPER(TRIM(B494))) -> Faisal Iqbal | D494: 0 | E494: =IFERROR(IF(Raw_Data!N490="", 0, IF(Raw_Data!N490>1, Raw_Data!N490/100, Raw_Data!N490)), 0) -> 0 | F494: =IFERROR(VALUE(Raw_Data!O490), Raw_Data!L490*Raw_Data!M490) -> 3584.56
B495: Adeel Sheikh | C495: =IF(OR(B495="",B495=0), "Unknown Customer", PROPER(TRIM(B495))) -> Adeel Sheikh | D495: 0.1 | E495: =IFERROR(IF(Raw_Data!N491="", 0, IF(Raw_Data!N491>1, Raw_Data!N491/100, Raw_Data!N491)), 0) -> 0.1 | F495: =IFERROR(VALUE(Raw_Data!O491), Raw_Data!L491*Raw_Data!M491) -> 3106.92
B496: Bilal Chaudhry | C496: =IF(OR(B496="",B496=0), "Unknown Customer", PROPER(TRIM(B496))) -> Bilal Chaudhry | D496: 0 | E496: =IFERROR(IF(Raw_Data!N492="", 0, IF(Raw_Data!N492>1, Raw_Data!N492/100, Raw_Data!N492)), 0) -> 0 | F496: =IFERROR(VALUE(Raw_Data!O492), Raw_Data!L492*Raw_Data!M492) -> 7242
B497: Omar Farooq | C497: =IF(OR(B497="",B497=0), "Unknown Customer", PROPER(TRIM(B497))) -> Omar Farooq | D497: 0 | E497: =IFERROR(IF(Raw_Data!N493="", 0, IF(Raw_Data!N493>1, Raw_Data!N493/100, Raw_Data!N493)), 0) -> 0 | F497: =IFERROR(VALUE(Raw_Data!O493), Raw_Data!L493*Raw_Data!M493) -> 7377.12
B498: Sara Qureshi | C498: =IF(OR(B498="",B498=0), "Unknown Customer", PROPER(TRIM(B498))) -> Sara Qureshi | D498: 0.2 | E498: =IFERROR(IF(Raw_Data!N494="", 0, IF(Raw_Data!N494>1, Raw_Data!N494/100, Raw_Data!N494)), 0) -> 0.2 | F498: =IFERROR(VALUE(Raw_Data!O494), Raw_Data!L494*Raw_Data!M494) -> 3440.2
...

Sheet Category_Summary
A1: Category-Wise Sales Summary (Pivot-style sanity check)
A2: Built with SUMIFS/COUNTIFS against Raw_Data — a quick sanity check before the data moves into SQL.
A4: Category | B4: Order Count | C4: Total Sales | D4: Total Profit
A5: Furniture | B5: =COUNTIF(Raw_Data!I:I,A5) -> 423 | C5: =SUMIF(Raw_Data!I:I,A5,Raw_Data!O:O) -> 1292635.8 | D5: =SUMIF(Raw_Data!I:I,A5,Raw_Data!P:P) -> 136611.15
A6: Office Supplies | B6: =COUNTIF(Raw_Data!I:I,Category_Summary!A6) -> 430 | C6: =SUMIF(Raw_Data!I:I,A6,Raw_Data!O:O) -> 1301622.1 | D6: =SUMIF(Raw_Data!I:I,A6,Raw_Data!P:P) -> 121206.68
A7: Technology | B7: =COUNTIF(Raw_Data!I:I,A7) -> 392 | C7: =SUMIF(Raw_Data!I:I,A7,Raw_Data!O:O) -> 1109618.4 | D7: =SUMIF(Raw_Data!I:I,A7,Raw_Data!P:P) -> 102322.87
A8: TOTAL | B8: =SUM(B5:B7) -> 1245 | C8: =SUM(C5:C7) -> 3703876.3 | D8: =SUM(D5:D7) -> 360140.7

Sheet Data_Quality_Notes
A1: Phase 1 — Data Quality Notes (Excel Review)
A4: Issue Found | B4: Action Taken
A5: Duplicate Order IDs (~45 rows) | B5: Flagged with conditional formatting here; removed properly in SQL using ROWID/MIN dedup logic (Phase 2).
A6: Blank Customer Name / Region / City / Ship Mode / Discount / Profit | B6: Flagged with conditional formatting; SQL view fills sensible defaults (e.g. 'Unknown Customer', 0 discount).
A7: Inconsistent text casing in Customer Name ('ALI KHAN', 'ali khan', ' Ali Khan ') | B7: TRIM()+PROPER() applied on Cleaning_Formulas sheet; standardized further in SQL.
A8: Region typos and case issues ('nort', 'NORTH', ' South ') | B8: Standardized to 5 canonical regions in SQL cleaning view using CASE/LOWER/TRIM.
A9: Negative Quantity values (data entry errors) | B9: Corrected using ABS() in SQL.
A10: Discount stored as whole numbers instead of decimals (e.g. 20 instead of 0.20) | B10: Detected and divided by 100 where Discount > 1, in both Excel formulas and SQL.
A11: Non-numeric 'N/A' values in Sales column | B11: IFERROR()+VALUE() fallback in Excel; SQL recomputes Sales = Quantity x Unit Price when invalid.
A12: Mixed date formats (YYYY-MM-DD and DD/MM/YYYY) | B12: Normalized to ISO format (YYYY-MM-DD) in the SQL cleaning view.
A13: One fully blank row | B13: Excluded in SQL WHERE clause (Order ID IS NOT NULL).
